Metadata-Version: 2.1
Name: CleanInput
Version: 0.0.2
Summary: Auto del input noise.
Home-page: UNKNOWN
Author: KurehaSHO
License: UNKNOWN
Keywords: pip,CleanInput
Platform: any
